optimnat/__init__.py
optimnat/funciones/__init__.py
optimnat/funciones/fun_restricciones.py
optimnat/funciones/fun_sin_restricciones.py
optimnat/multivariable/__init__.py
optimnat/multivariable/directos/__init__.py
optimnat/multivariable/directos/caminata_aleatoria.py
optimnat/multivariable/directos/hooke_jeeves.py
optimnat/multivariable/directos/nelder_mead.py
optimnat/multivariable/gradiente/__init__.py
optimnat/multivariable/gradiente/cauchy.py
optimnat/multivariable/gradiente/fletcher_reeves.py
optimnat/multivariable/gradiente/newton.py
optimnat/univariable/__init__.py
optimnat/univariable/derivada/__init__.py
optimnat/univariable/derivada/biseccion.py
optimnat/univariable/derivada/newton_raphson.py
optimnat/univariable/derivada/secante.py
optimnat/univariable/eliminacion_regiones/__init__.py
optimnat/univariable/eliminacion_regiones/busqueda_fibonacci.py
optimnat/univariable/eliminacion_regiones/division_intervalos.py
optimnat/univariable/eliminacion_regiones/seccion_dorada.py
optimnat-0.1.1.dist-info/LICENSE
optimnat-0.1.1.dist-info/METADATA
optimnat-0.1.1.dist-info/WHEEL
optimnat-0.1.1.dist-info/top_level.txt
optimnat-0.1.1.dist-info/RECORD
