Metadata-Version: 2.1
Name: optimnat
Version: 0.1.1
Summary: Paquete de métodos de optimización para funciones de una variable y multivariables
Home-page: https://github.com/n4tJM/optimnat_project
Author: Natalia Jarquin
Author-email: ux21ii179@ux.edu.mx
Classifier: Programming Language :: Python :: 3
Classifier: License :: OSI Approved :: MIT License
Classifier: Operating System :: OS Independent
Requires-Python: >=3.8
License-File: LICENSE
